<workflow scriptid="customworkflow_ptg_folio_nota_anden">
  <description></description>
  <initcontexts>ACTION|BANKCONNECTIVITY|BANKSTATEMENTPARSER|BUNDLEINSTALLATION|CLIENT|CSVIMPORT|CUSTOMGLLINES|CUSTOMMASSUPDATE|RECORDACTION|DATASETBUILDER|DEBUGGER|EMAILCAPTURE|FICONNECTIVITY|FIPARSER|MAPREDUCE|OFFLINECLIENT|OTHER|PAYMENTPOSTBACK|PAYMENTGATEWAY|PLATFORMEXTENSION|PORTLET|PROMOTIONS|CONSOLRATEADJUSTOR|RESTWEBSERVICES|RESTLET|ADVANCEDREVREC|SCHEDULED|SDFINSTALLATION|SHIPPINGPARTNERS|WEBSERVICES|SUITELET|TAXCALCULATION|USEREVENT|USERINTERFACE|WORKBOOKBUILDER|WORKFLOW</initcontexts>
  <initeventtypes></initeventtypes>
  <initlocalizationcontext></initlocalizationcontext>
  <initoncreate>T</initoncreate>
  <initonvieworupdate>T</initonvieworupdate>
  <initsavedsearchcondition></initsavedsearchcondition>
  <inittriggertype></inittriggertype>
  <isinactive>F</isinactive>
  <islogenabled>F</islogenabled>
  <keephistory>ONLYWHENTESTING</keephistory>
  <name>PTG - Folio de nota</name>
  <recordtypes>[scriptid=customrecord_ptg_venta_anden]</recordtypes>
  <releasestatus>SUSPENDED</releasestatus>
  <runasadmin>T</runasadmin>
  <initcondition>
    <formula></formula>
    <type>VISUAL_BUILDER</type>
  </initcondition>
  <workflowstates>
    <workflowstate scriptid="workflowstate2597">
      <description></description>
      <donotexitworkflow>F</donotexitworkflow>
      <name>Estado 1</name>
      <positionx>243</positionx>
      <positiony>133</positiony>
      <workflowactions triggertype="BEFORELOAD">
        <setdisplaytypeaction scriptid="workflowaction14438">
          <clienttriggerfields></clienttriggerfields>
          <conditionsavedsearch></conditionsavedsearch>
          <contexttypes>ACTION|BANKCONNECTIVITY|BANKSTATEMENTPARSER|BUNDLEINSTALLATION|CLIENT|CSVIMPORT|CUSTOMGLLINES|CUSTOMMASSUPDATE|RECORDACTION|DATASETBUILDER|DEBUGGER|EMAILCAPTURE|FICONNECTIVITY|FIPARSER|MAPREDUCE|OFFLINECLIENT|OTHER|PAYMENTPOSTBACK|PAYMENTGATEWAY|PLATFORMEXTENSION|PORTLET|PROMOTIONS|CONSOLRATEADJUSTOR|RESTWEBSERVICES|RESTLET|ADVANCEDREVREC|SCHEDULED|SDFINSTALLATION|SHIPPINGPARTNERS|WEBSERVICES|SUITELET|TAXCALCULATION|USEREVENT|USERINTERFACE|WORKBOOKBUILDER|WORKFLOW</contexttypes>
          <displaytype>DISABLED</displaytype>
          <eventtypes></eventtypes>
          <field>[scriptid=customrecord_ptg_venta_anden.custrecord_ptg_folio_nota_anden]</field>
          <isinactive>F</isinactive>
          <issublistfield>F</issublistfield>
          <initcondition>
            <formula><![CDATA[isChecked("PTG - Cliente Solicita Factura") = 'F']]></formula>
            <type>VISUAL_BUILDER</type>
            <parameters>
              <parameter>
                <name>PTG - Cliente Solicita Factura</name>
                <value>[scriptid=customrecord_ptg_venta_anden.custrecord_ptg_requiere_factura_anden]</value>
              </parameter>
            </parameters>
          </initcondition>
        </setdisplaytypeaction>
        <setdisplaytypeaction scriptid="workflowaction14439">
          <clienttriggerfields></clienttriggerfields>
          <conditionsavedsearch></conditionsavedsearch>
          <contexttypes>ACTION|BANKCONNECTIVITY|BANKSTATEMENTPARSER|BUNDLEINSTALLATION|CLIENT|CSVIMPORT|CUSTOMGLLINES|CUSTOMMASSUPDATE|RECORDACTION|DATASETBUILDER|DEBUGGER|EMAILCAPTURE|FICONNECTIVITY|FIPARSER|MAPREDUCE|OFFLINECLIENT|OTHER|PAYMENTPOSTBACK|PAYMENTGATEWAY|PLATFORMEXTENSION|PORTLET|PROMOTIONS|CONSOLRATEADJUSTOR|RESTWEBSERVICES|RESTLET|ADVANCEDREVREC|SCHEDULED|SDFINSTALLATION|SHIPPINGPARTNERS|WEBSERVICES|SUITELET|TAXCALCULATION|USEREVENT|USERINTERFACE|WORKBOOKBUILDER|WORKFLOW</contexttypes>
          <displaytype>NORMAL</displaytype>
          <eventtypes></eventtypes>
          <field>[scriptid=customrecord_ptg_venta_anden.custrecord_ptg_folio_nota_anden]</field>
          <isinactive>F</isinactive>
          <issublistfield>F</issublistfield>
          <initcondition>
            <formula><![CDATA[isChecked("PTG - Cliente Solicita Factura") = 'T']]></formula>
            <type>VISUAL_BUILDER</type>
            <parameters>
              <parameter>
                <name>PTG - Cliente Solicita Factura</name>
                <value>[scriptid=customrecord_ptg_venta_anden.custrecord_ptg_requiere_factura_anden]</value>
              </parameter>
            </parameters>
          </initcondition>
        </setdisplaytypeaction>
      </workflowactions>
      <workflowactions triggertype="AFTERFIELDEDIT">
        <setdisplaytypeaction scriptid="workflowaction14436">
          <clienttriggerfields>[scriptid=customrecord_ptg_venta_anden.custrecord_ptg_requiere_factura_anden]</clienttriggerfields>
          <conditionsavedsearch></conditionsavedsearch>
          <contexttypes>ACTION|BANKCONNECTIVITY|BANKSTATEMENTPARSER|BUNDLEINSTALLATION|CLIENT|CSVIMPORT|CUSTOMGLLINES|CUSTOMMASSUPDATE|RECORDACTION|DATASETBUILDER|DEBUGGER|EMAILCAPTURE|FICONNECTIVITY|FIPARSER|MAPREDUCE|OFFLINECLIENT|OTHER|PAYMENTPOSTBACK|PAYMENTGATEWAY|PLATFORMEXTENSION|PORTLET|PROMOTIONS|CONSOLRATEADJUSTOR|RESTWEBSERVICES|RESTLET|ADVANCEDREVREC|SCHEDULED|SDFINSTALLATION|SHIPPINGPARTNERS|WEBSERVICES|SUITELET|TAXCALCULATION|USEREVENT|USERINTERFACE|WORKBOOKBUILDER|WORKFLOW</contexttypes>
          <displaytype>NORMAL</displaytype>
          <eventtypes></eventtypes>
          <field>[scriptid=customrecord_ptg_venta_anden.custrecord_ptg_folio_nota_anden]</field>
          <isinactive>F</isinactive>
          <issublistfield>F</issublistfield>
          <initcondition>
            <formula><![CDATA[isChecked("PTG - Cliente Solicita Factura") = 'T']]></formula>
            <type>VISUAL_BUILDER</type>
            <parameters>
              <parameter>
                <name>PTG - Cliente Solicita Factura</name>
                <value>[scriptid=customrecord_ptg_venta_anden.custrecord_ptg_requiere_factura_anden]</value>
              </parameter>
            </parameters>
          </initcondition>
        </setdisplaytypeaction>
        <setdisplaytypeaction scriptid="workflowaction14437">
          <clienttriggerfields>[scriptid=customrecord_ptg_venta_anden.custrecord_ptg_requiere_factura_anden]</clienttriggerfields>
          <conditionsavedsearch></conditionsavedsearch>
          <contexttypes>ACTION|BANKCONNECTIVITY|BANKSTATEMENTPARSER|BUNDLEINSTALLATION|CLIENT|CSVIMPORT|CUSTOMGLLINES|CUSTOMMASSUPDATE|RECORDACTION|DATASETBUILDER|DEBUGGER|EMAILCAPTURE|FICONNECTIVITY|FIPARSER|MAPREDUCE|OFFLINECLIENT|OTHER|PAYMENTPOSTBACK|PAYMENTGATEWAY|PLATFORMEXTENSION|PORTLET|PROMOTIONS|CONSOLRATEADJUSTOR|RESTWEBSERVICES|RESTLET|ADVANCEDREVREC|SCHEDULED|SDFINSTALLATION|SHIPPINGPARTNERS|WEBSERVICES|SUITELET|TAXCALCULATION|USEREVENT|USERINTERFACE|WORKBOOKBUILDER|WORKFLOW</contexttypes>
          <displaytype>DISABLED</displaytype>
          <eventtypes></eventtypes>
          <field>[scriptid=customrecord_ptg_venta_anden.custrecord_ptg_folio_nota_anden]</field>
          <isinactive>F</isinactive>
          <issublistfield>F</issublistfield>
          <initcondition>
            <formula><![CDATA[isChecked("PTG - Cliente Solicita Factura") = 'F']]></formula>
            <type>VISUAL_BUILDER</type>
            <parameters>
              <parameter>
                <name>PTG - Cliente Solicita Factura</name>
                <value>[scriptid=customrecord_ptg_venta_anden.custrecord_ptg_requiere_factura_anden]</value>
              </parameter>
            </parameters>
          </initcondition>
        </setdisplaytypeaction>
      </workflowactions>
    </workflowstate>
  </workflowstates>
</workflow>